qtars/__init__.py
qtars/version.py
q_tars-0.0.0.dist-info/LICENSE
q_tars-0.0.0.dist-info/METADATA
q_tars-0.0.0.dist-info/WHEEL
q_tars-0.0.0.dist-info/top_level.txt
q_tars-0.0.0.dist-info/RECORD
