Metadata-Version: 2.1
Name: q-tars
Version: 0.0.0
Summary: Q-TARS: Omini Agent Framework based on Multi-modal Reinforcement Learning
Home-page: https://github.com/wabc/Q-TARS
Author: wangxingjun778
Author-email: wangxingjun778@163.com
License: Apache License 2.0
Keywords: Multi-modal,Agent,RL
License-File: LICENSE
